llsd2json/__init__.py
llsd2json/cli.py
llsd2json-1.0.0.dist-info/LICENSE
llsd2json-1.0.0.dist-info/METADATA
llsd2json-1.0.0.dist-info/WHEEL
llsd2json-1.0.0.dist-info/entry_points.txt
llsd2json-1.0.0.dist-info/top_level.txt
llsd2json-1.0.0.dist-info/RECORD
