Metadata-Version: 2.1
Name: llsd2json
Version: 1.0.0
Summary: CLIs to convert between LLSD and JSON
Author-email: Bennett Goble <151138+bennettgoble@users.noreply.github.com>
License: MIT
Project-URL: Homepage, https://github.com/bennettgoble/llsd2json
Classifier: Intended Audience :: Developers
Classifier: License :: OSI Approved :: MIT License
Classifier: Operating System :: OS Independent
Classifier: Programming Language :: Python :: 3
License-File: LICENSE
Requires-Dist: llsd
Requires-Dist: importlib-metadata ; python_version < "3.8"
Provides-Extra: dev
Requires-Dist: pytest ; extra == 'dev'
Requires-Dist: pytest-cov ; extra == 'dev'
